dotdict/__init__.py
dotdict/dotdict.py
dotdict_plus-1.0.3.dist-info/METADATA
dotdict_plus-1.0.3.dist-info/WHEEL
dotdict_plus-1.0.3.dist-info/top_level.txt
dotdict_plus-1.0.3.dist-info/RECORD
