Metadata-Version: 2.4
Name: dotdict-plus
Version: 1.0.3
Summary: A Python library for dot notation access to nested dictionaries
Author-email: Jiangbin <07jiangbin@gmail.com>
License: MIT
Project-URL: Homepage, https://git.xmov.ai/jiangbin/dot-dict
Project-URL: Repository, https://git.xmov.ai/jiangbin/dot-dict
Project-URL: Issues, https://git.xmov.ai/jiangbin/dot-dict
Keywords: python,dictionary,dot-notation,nested,data-structure
Classifier: Development Status :: 3 - Alpha
Classifier: Intended Audience :: Developers
Classifier: License :: OSI Approved :: MIT License
Classifier: Operating System :: OS Independent
Classifier: Programming Language :: Python :: 3
Classifier: Programming Language :: Python :: 3.6
Classifier: Programming Language :: Python :: 3.7
Classifier: Programming Language :: Python :: 3.8
Classifier: Programming Language :: Python :: 3.9
Classifier: Programming Language :: Python :: 3.10
Classifier: Programming Language :: Python :: 3.11
Classifier: Programming Language :: Python :: 3.12
Classifier: Topic :: Software Development :: Libraries :: Python Modules
Requires-Python: >=3.6
Provides-Extra: dev
Requires-Dist: twine; extra == "dev"
Requires-Dist: pip-tools; extra == "dev"
Requires-Dist: build; extra == "dev"
Requires-Dist: pytest>=6.0; extra == "dev"
Requires-Dist: pytest-cov>=2.0; extra == "dev"
Requires-Dist: black>=22.0; extra == "dev"
Requires-Dist: flake8>=4.0; extra == "dev"
Requires-Dist: mypy>=0.900; extra == "dev"
